{
    "id": 127,
    "url": "https://en.numista.com/catalogue/pieces127.html",
    "title": "1 Euro (1st map)",
    "category": "coin",
    "issuer": {
        "code": "irlande",
        "name": "Ireland"
    },
    "min_year": 2002,
    "max_year": 2006,
    "type": "Standard circulation coin",
    "ruler": [
        {
            "id": 2858,
            "name": "Republic"
        }
    ],
    "value": {
        "text": "1 Euro",
        "numeric_value": 1,
        "numerator": "1",
        "denominator": 1,
        "currency": {
            "id": 9009,
            "name": "Euro",
            "full_name": "Euro (2002-date)"
        }
    },
    "demonetization": {
        "is_demonetized": false
    },
    "shape": "Round",
    "composition": {
        "text": "Bimetallic: copper-nickel clad nickel centre in nickel brass ring"
    },
    "technique": {
        "text": "Milled"
    },
    "obverse": {
        "engravers": [
            "Jarlath Hayes"
        ],
        "description": "The Celtic harp, a traditional symbol of Ireland, accompanied with the country name to the left, the date to the right, and the 12 stars of Europe in the outer rim",
        "lettering": "\u00e9ire 2003",
        "lettering_translation": "Ireland 2003",
        "picture": "https://en.numista.com/catalogue/photos/irlande/987-original.jpg",
        "thumbnail": "https://en.numista.com/catalogue/photos/irlande/987-180.jpg",
        "picture_copyright": "Ma collection de monnaies",
        "picture_copyright_url": "https://monnaiesetvarietes.numista.com/"
    },
    "reverse": {
        "engravers": [
            "Luc Luycx"
        ],
        "description": "A map, next to the face value, shows the gathering of the fifteen states of the European Union",
        "lettering": "1 EURO LL",
        "picture": "https://en.numista.com/catalogue/photos/irlande/988-original.jpg",
        "thumbnail": "https://en.numista.com/catalogue/photos/irlande/988-180.jpg",
        "picture_copyright": "Ma collection de monnaies",
        "picture_copyright_url": "https://monnaiesetvarietes.numista.com/"
    },
    "related_types": [
        {
            "id": 6333,
            "title": "1 Euro (2nd map)",
            "category": "coin",
            "country": {
                "code": "irlande",
                "name": "Ireland"
            },
            "minYear": 2007,
            "maxYear": 2022
        }
    ],
    "tags": [
        "Map"
    ],
    "references": [
        {
            "catalogue": {
                "id": 3,
                "code": "KM"
            },
            "number": "38"
        },
        {
            "catalogue": {
                "id": 24,
                "code": "Sch\u00f6n"
            },
            "number": "37"
        }
    ],
    "weight": 7.5,
    "size": 23.25,
    "thickness": 2.33,
    "orientation": "medal",
    "edge": {
        "description": "Alternating segments: three smooth, three finely ribbed",
        "picture": "https://en.numista.com/catalogue/photos/irlande/854-original.jpg",
        "thumbnail": "https://en.numista.com/catalogue/photos/irlande/854-180.jpg",
        "picture_copyright": "Cyrillius",
        "picture_license_name": "CC BY",
        "picture_license_url": "https://creativecommons.org/licenses/by/4.0/deed.en"
    },
    "mints": [
        {
            "id": "1318",
            "name": "Irish Mint"
        }
    ]
}