{
    "id": 275891,
    "url": "https://en.numista.com/catalogue/pieces275891.html",
    "title": "2 Euro (UNICEF)",
    "category": "coin",
    "issuer": {
        "code": "france",
        "name": "France"
    },
    "min_year": 2021,
    "max_year": 2021,
    "type": "Circulating commemorative coin",
    "ruler": [
        {
            "id": 11,
            "name": "Fifth Republic",
            "wikidata_id": "Q200686",
            "group": {
                "id": 89,
                "name": "Modern France"
            }
        }
    ],
    "value": {
        "text": "2 Euro",
        "numeric_value": 2,
        "numerator": "2",
        "denominator": 1,
        "currency": {
            "id": 9006,
            "name": "Euro",
            "full_name": "Euro (2002-date)"
        }
    },
    "demonetization": {
        "is_demonetized": false
    },
    "shape": "Round",
    "composition": {
        "text": "Bimetallic: nickel brass clad nickel centre in copper-nickel ring"
    },
    "technique": {
        "text": "Milled"
    },
    "obverse": {
        "description": "The design shows an allegory of the work of \u2018UNICEF\u2019 where the hands are a key element. One after the other they support the globe and are the link between the different areas of the Earth. The mention of the 75th anniversary as well as the laurels crown the ensemble accompanied by the acronym RF. On the upper rim, the name \u2018UNICEF\u2019 is inserted along with the relevant dates as well as the UNICEF motto \u2018For each child\u2019.\r\nThe coin\u2019s outer ring depicts the 12 stars of the European flag.",
        "lettering": "UNICEF \r\n1946 \u2013 2021 \r\nPOUR CHAQUE ENFANT\r\n75 ANS\r\nRF",
        "lettering_scripts": [
            {
                "name": "Latin"
            }
        ],
        "lettering_translation": "For each child\r\n75 years",
        "picture": "https://en.numista.com/catalogue/photos/france/62ba04a89f8033.99285774-original.jpg",
        "thumbnail": "https://en.numista.com/catalogue/photos/france/62ba04a89f8033.99285774-180.jpg",
        "picture_copyright": "adinumismatics"
    },
    "reverse": {
        "engravers": [
            "Luc Luycx"
        ],
        "description": "A geographical map of Western Europe spans the outer ring and inner core on the right side of the coin. The inscription 2 EURO is superimposed over the map of Europe, with the numeral \u201c2\u201d located in an open field representing the eastern Atlantic Ocean.\r\n12 stars are located on the right side of the outer ring, with six stars atop the map of Europe and six stars below it; six vertical stripes cut across the inner core of the coin, visually connecting the upper and lower star segments.",
        "lettering": "2 EURO\r\nLL",
        "lettering_scripts": [
            {
                "name": "Latin"
            }
        ],
        "picture": "https://en.numista.com/catalogue/photos/france/62ba04a9235d29.16063723-original.jpg",
        "thumbnail": "https://en.numista.com/catalogue/photos/france/62ba04a9235d29.16063723-180.jpg",
        "picture_copyright": "adinumismatics"
    },
    "commemorated_topic": "75 Years of UNICEF",
    "tags": [
        "Map",
        "Education",
        "Hand"
    ],
    "references": [
        {
            "catalogue": {
                "id": 3,
                "code": "KM"
            },
            "number": "2944"
        }
    ],
    "weight": 8.5,
    "size": 25.75,
    "thickness": 2.2,
    "orientation": "medal",
    "edge": {
        "description": "Reeded with inscription",
        "lettering": "2 ** 2 ** 2 ** 2 ** 2 ** 2 **",
        "picture": "https://en.numista.com/catalogue/photos/france/6032a9831adef4.71580122-original.jpg",
        "thumbnail": "https://en.numista.com/catalogue/photos/france/6032a9831adef4.71580122-180.jpg",
        "picture_copyright": "Cyrillius",
        "picture_license_name": "CC BY",
        "picture_license_url": "https://creativecommons.org/licenses/by/4.0/deed.en"
    },
    "mints": [
        {
            "id": "15",
            "name": "Paris Mint"
        }
    ]
}