{
    "id": 41904,
    "url": "https://en.numista.com/catalogue/pieces41904.html",
    "title": "2 Euro (\u00c9lys\u00e9e Treaty)",
    "category": "coin",
    "issuer": {
        "code": "france",
        "name": "France"
    },
    "min_year": 2013,
    "max_year": 2013,
    "type": "Circulating commemorative coin",
    "ruler": [
        {
            "id": 11,
            "name": "Fifth Republic",
            "wikidata_id": "Q200686",
            "group": {
                "id": 89,
                "name": "Modern France"
            }
        }
    ],
    "value": {
        "text": "2 Euro",
        "numeric_value": 2,
        "numerator": "2",
        "denominator": 1,
        "currency": {
            "id": 9006,
            "name": "Euro",
            "full_name": "Euro (2002-date)"
        }
    },
    "demonetization": {
        "is_demonetized": false
    },
    "shape": "Round",
    "composition": {
        "text": "Bimetallic: nickel brass clad nickel centre in copper-nickel ring"
    },
    "technique": {
        "text": "Milled"
    },
    "obverse": {
        "engravers": [
            "Stefanie Lindner",
            "Yves Sampo",
            "Alina Hoyer",
            "Sneschana Russewa-Hoyer"
        ],
        "description": "The coin, which was designed by Yves Sampo (Monnaie de Paris), Stefanie Lindner (Berlin State Mint), Alina Hoyer (Berlin) and Sneschana Russewa-Hoyer (Berlin), depicts stylised portraits of the signatories to the \u00c9lys\u00e9e Treaty (Konrad Adenauer, then Chancellor of the Federal Republic of Germany, and Charles de Gaulle, former President of the French Republic) above their respective signatures on either side of the words \u201c50 ANS JAHRE\u201d and the year \u201c2013\u201d in the centre. The words \u201cTRAIT\u00c9 DE L\u2019\u00c9LYS\u00c9E\u201d and \u201c\u00c9LYS\u00c9E-VERTRAG\u201d are centred along the top and bottom edge, respectively, of the inner part of the coin. On the right-hand inner edge below the portrait of Adenauer, the inner part also features the \u201cfleurette\u201d (hallmark of the engraving workshop) and the letters \u201cRF\u201d to denote the issuing country, while the mint mark is located on the coin\u2019s left-hand inner edge below the portrait of de Gaulle. The coin\u2019s outer ring bears the 12 stars of the European Union.",
        "lettering": "TRAIT\u00c9\r\nDE L'\u00c9LYS\u00c9E\r\n50\r\nANS\r\nJAHRE\r\n2013\r\n\u00c9LYS\u00c9E-\r\nVERTRAG\r\nRF",
        "lettering_translation": "\u00c9lys\u00e9e Treaty\r\n50 Years",
        "picture": "https://en.numista.com/catalogue/photos/france/5145-original.jpg",
        "thumbnail": "https://en.numista.com/catalogue/photos/france/5145-180.jpg",
        "picture_copyright": "bofried"
    },
    "reverse": {
        "engravers": [
            "Luc Luycx"
        ],
        "description": "A map, next to the face value, shows the European continent without borders.",
        "lettering": "2 EURO LL",
        "picture": "https://en.numista.com/catalogue/photos/france/5146-original.jpg",
        "thumbnail": "https://en.numista.com/catalogue/photos/france/5146-180.jpg",
        "picture_copyright": "bofried"
    },
    "commemorated_topic": "50th Anniversary of the \u00c9lys\u00e9e Treaty",
    "comments": "coincard<br />\r\n<a href=\"https://en.numista.com/catalogue/images/5c2e66c64048a.jpg\"Group=\"bb483864952\"><img src=\"https://en.numista.com/catalogue/images/miniatures/5c2e66c64048a.jpg\" alt=\"\" width=\"200\" height=\"176\" /></a>",
    "related_types": [
        {
            "id": 62852,
            "title": "5 Euro (Treaty of Elys\u00e9e)",
            "category": "coin",
            "country": {
                "code": "france",
                "name": "France"
            },
            "minYear": 2013,
            "maxYear": 2013
        },
        {
            "id": 43690,
            "title": "10 Euro (Elys\u00e9e Treaty)",
            "category": "coin",
            "country": {
                "code": "france",
                "name": "France"
            },
            "minYear": 2013,
            "maxYear": 2013
        },
        {
            "id": 124545,
            "title": "50 Euro (\u00c9lys\u00e9e Treaty)",
            "category": "coin",
            "country": {
                "code": "france",
                "name": "France"
            },
            "minYear": 2013,
            "maxYear": 2013
        },
        {
            "id": 117795,
            "title": "200 Euro (\u00c9lys\u00e9e Treaty)",
            "category": "coin",
            "country": {
                "code": "france",
                "name": "France"
            },
            "minYear": 2013,
            "maxYear": 2013
        },
        {
            "id": 171499,
            "title": "500 Euro (\u00c9lys\u00e9e Treaty)",
            "category": "coin",
            "country": {
                "code": "france",
                "name": "France"
            },
            "minYear": 2013,
            "maxYear": 2013
        },
        {
            "id": 41786,
            "title": "2 Euro (\u00c9lys\u00e9e Treaty)",
            "category": "coin",
            "country": {
                "code": "allemagne",
                "name": "Germany, Federal Republic of"
            },
            "minYear": 2013,
            "maxYear": 2013
        }
    ],
    "tags": [
        "Treaty",
        "Politician"
    ],
    "references": [
        {
            "catalogue": {
                "id": 3,
                "code": "KM"
            },
            "number": "2094"
        },
        {
            "catalogue": {
                "id": 24,
                "code": "Sch\u00f6n"
            },
            "number": "1334"
        },
        {
            "catalogue": {
                "id": 109,
                "code": "Gad"
            },
            "number": "17 (Ed.2019)"
        }
    ],
    "weight": 8.5,
    "size": 25.75,
    "thickness": 2.2,
    "orientation": "medal",
    "edge": {
        "description": "Finely ribbed with edge lettering: three times the sequence \"2 * *\" upright and the sequence \"* * 2\" inverted",
        "lettering": "2 ** 2 ** 2 ** 2 ** 2 ** 2 **",
        "picture": "https://en.numista.com/catalogue/photos/france/7459-original.jpg",
        "thumbnail": "https://en.numista.com/catalogue/photos/france/7459-180.jpg",
        "picture_copyright": "Cyrillius",
        "picture_license_name": "CC BY",
        "picture_license_url": "https://creativecommons.org/licenses/by/4.0/deed.en"
    },
    "mints": [
        {
            "id": "15",
            "name": "Paris Mint"
        }
    ]
}