{
    "id": 58,
    "url": "https://en.numista.com/catalogue/pieces58.html",
    "title": "2 Euro Cent",
    "category": "coin",
    "issuer": {
        "code": "autriche",
        "name": "Austria"
    },
    "min_year": 2002,
    "max_year": 2022,
    "type": "Standard circulation coin",
    "ruler": [
        {
            "id": 149,
            "name": "Second Republic"
        }
    ],
    "value": {
        "text": "2 Euro Cent",
        "numeric_value": 0.02,
        "currency": {
            "id": 9002,
            "name": "Euro",
            "full_name": "Euro (2002-date)"
        }
    },
    "demonetization": {
        "is_demonetized": false
    },
    "shape": "Round",
    "composition": {
        "text": "Copper plated steel"
    },
    "technique": {
        "text": "Milled"
    },
    "obverse": {
        "engravers": [
            "Josef Kaiser"
        ],
        "description": "An edelweiss, symbolising a duty to the environment, is encircled by the face value, heraldic hatchings representing the Austrian flag and the twelve stars of Europe",
        "lettering": "ZWEI EURO CENT 2013",
        "lettering_scripts": [
            {
                "name": "Latin"
            }
        ],
        "lettering_translation": "TWO EURO CENT 2013",
        "picture": "https://en.numista.com/catalogue/photos/autriche/621339f8972019.30788998-original.jpg",
        "thumbnail": "https://en.numista.com/catalogue/photos/autriche/621339f8972019.30788998-180.jpg",
        "picture_copyright": "Mike Bentley"
    },
    "reverse": {
        "engravers": [
            "Luc Luycx"
        ],
        "description": "A globe, next to the face value, shows Europe in relation to Africa and Asia",
        "lettering": "2 EURO CENT LL",
        "lettering_scripts": [
            {
                "name": "Latin"
            }
        ],
        "picture": "https://en.numista.com/catalogue/photos/autriche/621339f98e9cc9.26512080-original.jpg",
        "thumbnail": "https://en.numista.com/catalogue/photos/autriche/621339f98e9cc9.26512080-180.jpg",
        "picture_copyright": "Mike Bentley"
    },
    "comments": "Edelweiss Flower Binomial Name: Leontopodium alpinum<br />\r\n<br />\r\n<a href=\"https://en.numista.com/catalogue/images/608ad9c603dfa.jpg\"Group=\"bb412097650\"><img src=\"https://en.numista.com/catalogue/images/miniatures/608ad9c603dfa.jpg\" alt=\"\" width=\"200\" height=\"150\" /></a><br />\r\n<br />\r\nNew version of the common side seen with 2018 coins. Main differences:<br />\r\n&nbsp;- Thicker and shorter numeral<br />\r\n&nbsp;- Rounded edges of the numeral<br />\r\n&nbsp;- Thicker font in &quot;EURO CENT&quot;<br />\r\n&nbsp;- Thicker lines with longer ends outside of stars<br />\r\nAlso from 2018 onwards, thinner and more numerous lines in the flag on the national side (21, 25 vs. 19, 22).<br />\r\n<a href=\"https://en.numista.com/catalogue/images/5ed22b0be7bef.jpg\"Group=\"bb412097650\"><img src=\"https://en.numista.com/catalogue/images/miniatures/5ed22b0be7bef.jpg\" alt=\"\" width=\"200\" height=\"200\" /></a>",
    "tags": [
        "Map",
        "Flower"
    ],
    "references": [
        {
            "catalogue": {
                "id": 3,
                "code": "KM"
            },
            "number": "3083"
        },
        {
            "catalogue": {
                "id": 24,
                "code": "Sch\u00f6n"
            },
            "number": "278"
        }
    ],
    "weight": 3.06,
    "size": 18.75,
    "thickness": 1.67,
    "orientation": "medal",
    "edge": {
        "description": "Smooth with a groove running circumferentially around the edge of the coin",
        "picture": "https://en.numista.com/catalogue/photos/autriche/3268-original.jpg",
        "thumbnail": "https://en.numista.com/catalogue/photos/autriche/3268-180.jpg",
        "picture_copyright": "Cyrillius",
        "picture_license_name": "CC BY",
        "picture_license_url": "https://creativecommons.org/licenses/by/4.0/deed.en"
    },
    "mints": [
        {
            "id": "232",
            "name": "Vienna"
        }
    ]
}