{
    "id": 68392,
    "url": "https://en.numista.com/catalogue/pieces68392.html",
    "title": "20 Euro Cent",
    "category": "coin",
    "issuer": {
        "code": "andorre",
        "name": "Andorra"
    },
    "min_year": 2014,
    "max_year": 2021,
    "type": "Standard circulation coin",
    "ruler": [
        {
            "id": 4700,
            "name": "Joan Enric Vives i Sic\u00edlia",
            "wikidata_id": "Q57473",
            "group": {
                "id": 377,
                "name": "Co-Principality"
            }
        }
    ],
    "value": {
        "text": "20 Euro Cent",
        "numeric_value": 0.2,
        "numerator": "20",
        "denominator": 100,
        "currency": {
            "id": 9024,
            "name": "Euro",
            "full_name": "Euro (2014-date)"
        }
    },
    "demonetization": {
        "is_demonetized": false
    },
    "shape": "Spanish flower",
    "composition": {
        "text": "Nordic gold (89% Copper, 5% Aluminium, 5% Zinc, 1% Tin)"
    },
    "technique": {
        "text": "Milled"
    },
    "obverse": {
        "engravers": [
            "Moles Disseny"
        ],
        "description": "At the center of the coin there is the Church of St. Coloma; right the year of mint and the inscription \"ANDORRA\". Around twelve five-pointed stars representing the European Union.",
        "lettering": "ANDORRA\r\n2017",
        "lettering_scripts": [
            {
                "name": "Latin"
            }
        ],
        "picture": "https://en.numista.com/catalogue/photos/andorre/626ea523311535.19251046-original.jpg",
        "thumbnail": "https://en.numista.com/catalogue/photos/andorre/626ea523311535.19251046-180.jpg",
        "picture_copyright": "Mike Bentley"
    },
    "reverse": {
        "engravers": [
            "Luc Luycx"
        ],
        "description": "A map, next to the face value, shows the European continent without borders",
        "lettering": "20 EURO CENT LL",
        "lettering_scripts": [
            {
                "name": "Latin"
            }
        ],
        "picture": "https://en.numista.com/catalogue/photos/andorre/626ea524508f27.41834763-original.jpg",
        "thumbnail": "https://en.numista.com/catalogue/photos/andorre/626ea524508f27.41834763-180.jpg",
        "picture_copyright": "Mike Bentley"
    },
    "related_types": [
        {
            "id": 68390,
            "title": "10 Euro Cent",
            "category": "coin",
            "country": {
                "code": "andorre",
                "name": "Andorra"
            },
            "minYear": 2014,
            "maxYear": 2021
        },
        {
            "id": 68393,
            "title": "50 Euro Cent",
            "category": "coin",
            "country": {
                "code": "andorre",
                "name": "Andorra"
            },
            "minYear": 2014,
            "maxYear": 2021
        }
    ],
    "tags": [
        "Religious building",
        "Map"
    ],
    "references": [
        {
            "catalogue": {
                "id": 3,
                "code": "KM"
            },
            "number": "524"
        },
        {
            "catalogue": {
                "id": 24,
                "code": "Sch\u00f6n"
            },
            "number": "505"
        }
    ],
    "weight": 5.74,
    "size": 22.25,
    "thickness": 2.14,
    "orientation": "medal",
    "edge": {
        "description": "Smooth with 7 Indentations (\"Spanish flower\")",
        "picture": "https://en.numista.com/catalogue/photos/andorre/573-original.jpg",
        "thumbnail": "https://en.numista.com/catalogue/photos/andorre/573-180.jpg",
        "picture_copyright": "Cyrillius",
        "picture_license_name": "CC BY",
        "picture_license_url": "https://creativecommons.org/licenses/by/4.0/deed.en"
    },
    "mints": [
        {
            "id": "15",
            "name": "Paris Mint"
        },
        {
            "id": "24",
            "name": "Royal Mint of Spain"
        }
    ]
}