{
    "id": 86935,
    "url": "https://en.numista.com/catalogue/pieces86935.html",
    "title": "2 Euro (Baltic Culture)",
    "category": "coin",
    "issuer": {
        "code": "lituanie",
        "name": "Lithuania"
    },
    "min_year": 2016,
    "max_year": 2016,
    "type": "Circulating commemorative coin",
    "ruler": [
        {
            "id": 2866,
            "name": "Republic"
        }
    ],
    "value": {
        "text": "2 Euro",
        "numeric_value": 2,
        "numerator": "2",
        "denominator": 1,
        "currency": {
            "id": 9023,
            "name": "Euro",
            "full_name": "Euro (2015-date)"
        }
    },
    "demonetization": {
        "is_demonetized": false
    },
    "shape": "Round",
    "composition": {
        "text": "Bimetallic: nickel brass clad nickel centre in copper-nickel ring"
    },
    "technique": {
        "text": "Milled"
    },
    "obverse": {
        "description": "An amber disc, one of the most characteristic symbols of the Baltic culture, decorated with a crosspiece of drilled dots \u2014 an ornament symbolising the world\u2019s axis. The country name is at the top flanked by the mint mark and the date. The coin\u2019s outer ring bears the 12 stars of the European Union.",
        "lettering": "LMK\r\nLIETUVA\r\n2016",
        "lettering_scripts": [
            {
                "name": "Latin"
            }
        ],
        "lettering_translation": "LMK\r\nLithuania\r\n2016",
        "picture": "https://en.numista.com/catalogue/photos/lituanie/885-original.jpg",
        "thumbnail": "https://en.numista.com/catalogue/photos/lituanie/885-180.jpg",
        "picture_copyright": "Ulmo"
    },
    "reverse": {
        "engravers": [
            "Luc Luycx"
        ],
        "description": "A map, next to the face value, shows the European continent without borders.",
        "lettering": "2 EURO\r\nLL",
        "lettering_scripts": [
            {
                "name": "Latin"
            }
        ],
        "picture": "https://en.numista.com/catalogue/photos/lituanie/886-original.jpg",
        "thumbnail": "https://en.numista.com/catalogue/photos/lituanie/886-180.jpg",
        "picture_copyright": "Ulmo"
    },
    "commemorated_topic": "The Baltic Culture",
    "comments": "Date of issue 03-05-2016",
    "references": [
        {
            "catalogue": {
                "id": 3,
                "code": "KM"
            },
            "number": "221"
        },
        {
            "catalogue": {
                "id": 24,
                "code": "Sch\u00f6n"
            },
            "number": "153"
        }
    ],
    "weight": 8.5,
    "size": 25.75,
    "thickness": 2.2,
    "orientation": "medal",
    "edge": {
        "description": "Reeded with inscription",
        "lettering": "LAISV\u0116 * VIENYB\u0116 * GEROV\u0116 *",
        "lettering_translation": "Freedom * Unity * Well-Being",
        "picture": "https://en.numista.com/catalogue/photos/lituanie/696-original.jpg",
        "thumbnail": "https://en.numista.com/catalogue/photos/lituanie/696-180.jpg",
        "picture_copyright": "Cyrillius",
        "picture_license_name": "CC BY",
        "picture_license_url": "https://creativecommons.org/licenses/by/4.0/deed.en"
    },
    "mints": [
        {
            "id": "1332",
            "name": "Lithuanian Mint"
        }
    ]
}