[
    {
        "id": 84747,
        "is_dated": true,
        "year": 2011,
        "gregorian_year": 2011,
        "mintage": 25071500
    },
    {
        "id": 132789,
        "is_dated": true,
        "year": 2011,
        "gregorian_year": 2011,
        "mintage": 50000,
        "comment": "In Sets only"
    },
    {
        "id": 139324,
        "is_dated": true,
        "year": 2011,
        "gregorian_year": 2011,
        "mintage": 3500,
        "comment": "Proof"
    },
    {
        "id": 302542,
        "is_dated": true,
        "year": 2016,
        "gregorian_year": 2016,
        "mintage": 20000,
        "comment": "In Sets only."
    },
    {
        "id": 333691,
        "is_dated": true,
        "year": 2017,
        "gregorian_year": 2017,
        "mintage": 3250000
    },
    {
        "id": 391555,
        "is_dated": true,
        "year": 2018,
        "gregorian_year": 2018,
        "mintage": 5000,
        "comment": "In Sets only. Mint of Finland; large stars"
    },
    {
        "id": 402363,
        "is_dated": true,
        "year": 2018,
        "gregorian_year": 2018,
        "mintage": 4000000,
        "comment": "large stars"
    },
    {
        "id": 582653,
        "is_dated": true,
        "year": 2020,
        "gregorian_year": 2020,
        "mintage": 1500000,
        "comment": "large stars"
    },
    {
        "id": 675775,
        "is_dated": true,
        "year": 2021,
        "gregorian_year": 2021,
        "mintage": 2000000
    }
]