[
    {
        "id": 1837,
        "is_dated": true,
        "year": 2001,
        "gregorian_year": 2001,
        "mintage": 300000
    },
    {
        "id": 131161,
        "is_dated": true,
        "year": 2001,
        "gregorian_year": 2001,
        "mintage": 20000,
        "comment": "In Sets only"
    },
    {
        "id": 131160,
        "is_dated": true,
        "year": 2001,
        "gregorian_year": 2001,
        "mintage": 3500,
        "comment": "Proof"
    },
    {
        "id": 1845,
        "is_dated": true,
        "year": 2002,
        "gregorian_year": 2002,
        "mintage": 367200
    },
    {
        "id": 131163,
        "is_dated": true,
        "year": 2002,
        "gregorian_year": 2002,
        "mintage": 40000,
        "comment": "In Sets only"
    },
    {
        "id": 1850,
        "is_dated": true,
        "year": 2003,
        "gregorian_year": 2003,
        "mintage": 100800
    },
    {
        "id": 1858,
        "is_dated": true,
        "year": 2004,
        "gregorian_year": 2004,
        "mintage": 14999,
        "comment": "Proof"
    }
]