[
    {
        "id": 9894,
        "is_dated": true,
        "year": 2008,
        "gregorian_year": 2008,
        "mint_letter": "F",
        "mintage": 10000000,
        "comment": "\"F\" mark in Star"
    },
    {
        "id": 133917,
        "is_dated": true,
        "year": 2008,
        "gregorian_year": 2008,
        "mint_letter": "F",
        "mintage": 50000,
        "comment": "\"F\" mark in Star; In Sets"
    },
    {
        "id": 140505,
        "is_dated": true,
        "year": 2011,
        "gregorian_year": 2011,
        "mintage": 50000,
        "comment": "Without NGB; In Sets"
    },
    {
        "id": 168890,
        "is_dated": true,
        "year": 2012,
        "gregorian_year": 2012,
        "mintage": 50000,
        "comment": "In Sets"
    },
    {
        "id": 216543,
        "is_dated": true,
        "year": 2013,
        "gregorian_year": 2013,
        "mintage": 11000000
    },
    {
        "id": 195510,
        "is_dated": true,
        "year": 2013,
        "gregorian_year": 2013,
        "mintage": 35000,
        "comment": "In Sets"
    },
    {
        "id": 236138,
        "is_dated": true,
        "year": 2014,
        "gregorian_year": 2014,
        "mintage": 25000,
        "comment": "In Sets"
    },
    {
        "id": 261928,
        "is_dated": true,
        "year": 2015,
        "gregorian_year": 2015
    },
    {
        "id": 261652,
        "is_dated": true,
        "year": 2015,
        "gregorian_year": 2015,
        "mintage": 30000,
        "comment": "In Sets"
    },
    {
        "id": 319064,
        "is_dated": true,
        "year": 2016,
        "gregorian_year": 2016,
        "mint_letter": "F",
        "mintage": 250000
    },
    {
        "id": 303518,
        "is_dated": true,
        "year": 2016,
        "gregorian_year": 2016,
        "mint_letter": "F",
        "mintage": 30000,
        "comment": "In Sets"
    },
    {
        "id": 396489,
        "is_dated": true,
        "year": 2017,
        "gregorian_year": 2017,
        "mintage": 6000000,
        "comment": "Without F"
    },
    {
        "id": 361809,
        "is_dated": true,
        "year": 2017,
        "gregorian_year": 2017,
        "mint_letter": "F"
    },
    {
        "id": 346706,
        "is_dated": true,
        "year": 2017,
        "gregorian_year": 2017,
        "mint_letter": "F",
        "mintage": 25000,
        "comment": "In Sets"
    },
    {
        "id": 398184,
        "is_dated": true,
        "year": 2018,
        "gregorian_year": 2018,
        "mint_letter": "F",
        "mintage": 21000000
    },
    {
        "id": 401491,
        "is_dated": true,
        "year": 2018,
        "gregorian_year": 2018,
        "mint_letter": "F",
        "mintage": 15000,
        "comment": "In Sets"
    },
    {
        "id": 679432,
        "is_dated": true,
        "year": 2019,
        "gregorian_year": 2019,
        "mint_letter": "F",
        "mintage": 5000000
    },
    {
        "id": 440052,
        "is_dated": true,
        "year": 2019,
        "gregorian_year": 2019,
        "mint_letter": "F",
        "mintage": 15000,
        "comment": "In Sets"
    },
    {
        "id": 574469,
        "is_dated": true,
        "year": 2020,
        "gregorian_year": 2020,
        "mint_letter": "F",
        "mintage": 10000,
        "comment": "In Sets"
    },
    {
        "id": 707329,
        "is_dated": true,
        "year": 2021,
        "gregorian_year": 2021,
        "mintage": 6500000
    },
    {
        "id": 686002,
        "is_dated": true,
        "year": 2021,
        "gregorian_year": 2021,
        "mint_letter": "F",
        "mintage": 11000,
        "comment": "In Sets"
    },
    {
        "id": 689910,
        "is_dated": true,
        "year": 2021,
        "gregorian_year": 2021,
        "mint_letter": "F",
        "mintage": 11000,
        "comment": "In Sets"
    }
]