[
    {
        "id": 675595,
        "is_dated": true,
        "year": 2021,
        "gregorian_year": 2021,
        "mintage": 2500,
        "comment": "(fr) BE (Pont / Lion)"
    },
    {
        "id": 675594,
        "is_dated": true,
        "year": 2021,
        "gregorian_year": 2021,
        "mintage": 2500,
        "comment": "(fr) BU (Pont / Caduc\u00e9e)"
    },
    {
        "id": 638257,
        "is_dated": true,
        "year": 2021,
        "gregorian_year": 2021,
        "mintage": 160000,
        "comment": "Lion / Caduc\u00e9e, in rools"
    }
]