[
    {
        "id": 26041,
        "is_dated": true,
        "year": 2009,
        "gregorian_year": 2009,
        "mintage": 42878000
    },
    {
        "id": 106502,
        "is_dated": true,
        "year": 2009,
        "gregorian_year": 2009,
        "mintage": 120000,
        "comment": "In Sets only"
    },
    {
        "id": 106503,
        "is_dated": true,
        "year": 2009,
        "gregorian_year": 2009,
        "mintage": 13000,
        "comment": "Proof"
    },
    {
        "id": 102676,
        "is_dated": true,
        "year": 2010,
        "gregorian_year": 2010,
        "mintage": 25000,
        "comment": "In Sets only"
    },
    {
        "id": 106501,
        "is_dated": true,
        "year": 2010,
        "gregorian_year": 2010,
        "mintage": 5000,
        "comment": "Proof"
    },
    {
        "id": 143748,
        "is_dated": true,
        "year": 2011,
        "gregorian_year": 2011,
        "mintage": 25000,
        "comment": "In Sets only"
    },
    {
        "id": 113202,
        "is_dated": true,
        "year": 2011,
        "gregorian_year": 2011,
        "mintage": 6000,
        "comment": "Proof"
    },
    {
        "id": 148973,
        "is_dated": true,
        "year": 2012,
        "gregorian_year": 2012,
        "mintage": 23000,
        "comment": "In Sets only"
    },
    {
        "id": 150373,
        "is_dated": true,
        "year": 2012,
        "gregorian_year": 2012,
        "mintage": 6000,
        "comment": "Proof"
    },
    {
        "id": 200170,
        "is_dated": true,
        "year": 2013,
        "gregorian_year": 2013,
        "mintage": 23500,
        "comment": "In Sets only"
    },
    {
        "id": 185577,
        "is_dated": true,
        "year": 2013,
        "gregorian_year": 2013,
        "mintage": 5500,
        "comment": "Proof"
    },
    {
        "id": 224595,
        "is_dated": true,
        "year": 2014,
        "gregorian_year": 2014,
        "mintage": 21500,
        "comment": "In Sets only"
    },
    {
        "id": 224594,
        "is_dated": true,
        "year": 2014,
        "gregorian_year": 2014,
        "mintage": 3500,
        "comment": "Proof"
    },
    {
        "id": 252974,
        "is_dated": true,
        "year": 2015,
        "gregorian_year": 2015,
        "mintage": 21500,
        "comment": "In Sets only"
    },
    {
        "id": 252973,
        "is_dated": true,
        "year": 2015,
        "gregorian_year": 2015,
        "mintage": 3500,
        "comment": "Proof"
    },
    {
        "id": 293979,
        "is_dated": true,
        "year": 2016,
        "gregorian_year": 2016,
        "mintage": 23000,
        "comment": "In Sets only"
    },
    {
        "id": 293980,
        "is_dated": true,
        "year": 2016,
        "gregorian_year": 2016,
        "mintage": 3000,
        "comment": "Proof"
    },
    {
        "id": 329630,
        "is_dated": true,
        "year": 2017,
        "gregorian_year": 2017,
        "mintage": 8000,
        "comment": "In 3 BU sets"
    },
    {
        "id": 415228,
        "is_dated": true,
        "year": 2017,
        "gregorian_year": 2017,
        "mintage": 3000,
        "comment": "Proof"
    },
    {
        "id": 383364,
        "is_dated": true,
        "year": 2018,
        "gregorian_year": 2018,
        "mintage": 3000,
        "comment": "In sets only"
    },
    {
        "id": 415229,
        "is_dated": true,
        "year": 2018,
        "gregorian_year": 2018,
        "mintage": 800,
        "comment": "Proof"
    },
    {
        "id": 432315,
        "is_dated": true,
        "year": 2019,
        "gregorian_year": 2019,
        "mintage": 6000,
        "comment": "In sets Only Ice Hockey world"
    },
    {
        "id": 535606,
        "is_dated": true,
        "year": 2020,
        "gregorian_year": 2020,
        "mintage": 5000,
        "comment": "(fr) BU (Jeux Olympiques Tokyo 2020)"
    },
    {
        "id": 535607,
        "is_dated": true,
        "year": 2020,
        "gregorian_year": 2020,
        "comment": "Proof"
    },
    {
        "id": 712591,
        "is_dated": true,
        "year": 2021,
        "gregorian_year": 2021,
        "mintage": 1425000
    },
    {
        "id": 660795,
        "is_dated": true,
        "year": 2021,
        "gregorian_year": 2021,
        "comment": "(fr) BU"
    },
    {
        "id": 712605,
        "is_dated": true,
        "year": 2022,
        "gregorian_year": 2022,
        "mintage": 11000,
        "comment": "BU set"
    },
    {
        "id": 712606,
        "is_dated": true,
        "year": 2022,
        "gregorian_year": 2022,
        "mintage": 1900,
        "comment": "proof set"
    }
]