[
    {
        "id": 217276,
        "is_dated": true,
        "year": 2014,
        "gregorian_year": 2014,
        "mint_letter": "A",
        "mintage": 6000000
    },
    {
        "id": 217277,
        "is_dated": true,
        "year": 2014,
        "gregorian_year": 2014,
        "mint_letter": "A",
        "mintage": 85000,
        "comment": "In Sets only"
    },
    {
        "id": 217278,
        "is_dated": true,
        "year": 2014,
        "gregorian_year": 2014,
        "mint_letter": "A",
        "mintage": 84000,
        "comment": "Proof"
    },
    {
        "id": 217279,
        "is_dated": true,
        "year": 2014,
        "gregorian_year": 2014,
        "mint_letter": "D",
        "mintage": 6300000
    },
    {
        "id": 217280,
        "is_dated": true,
        "year": 2014,
        "gregorian_year": 2014,
        "mint_letter": "D",
        "mintage": 80000,
        "comment": "In Sets only"
    },
    {
        "id": 217281,
        "is_dated": true,
        "year": 2014,
        "gregorian_year": 2014,
        "mint_letter": "D",
        "mintage": 77000,
        "comment": "Proof"
    },
    {
        "id": 217282,
        "is_dated": true,
        "year": 2014,
        "gregorian_year": 2014,
        "mint_letter": "F",
        "mintage": 7200000
    },
    {
        "id": 217283,
        "is_dated": true,
        "year": 2014,
        "gregorian_year": 2014,
        "mint_letter": "F",
        "mintage": 80000,
        "comment": "In Sets only"
    },
    {
        "id": 217284,
        "is_dated": true,
        "year": 2014,
        "gregorian_year": 2014,
        "mint_letter": "F",
        "mintage": 77000,
        "comment": "Proof"
    },
    {
        "id": 217285,
        "is_dated": true,
        "year": 2014,
        "gregorian_year": 2014,
        "mint_letter": "G",
        "mintage": 4200000
    },
    {
        "id": 218315,
        "is_dated": true,
        "year": 2014,
        "gregorian_year": 2014,
        "mint_letter": "G",
        "mintage": 80000,
        "comment": "In Sets only"
    },
    {
        "id": 218316,
        "is_dated": true,
        "year": 2014,
        "gregorian_year": 2014,
        "mint_letter": "G",
        "mintage": 77000,
        "comment": "Proof"
    },
    {
        "id": 218317,
        "is_dated": true,
        "year": 2014,
        "gregorian_year": 2014,
        "mint_letter": "J",
        "mintage": 6300000
    },
    {
        "id": 218319,
        "is_dated": true,
        "year": 2014,
        "gregorian_year": 2014,
        "mint_letter": "J",
        "mintage": 80000,
        "comment": "In Sets only"
    },
    {
        "id": 218318,
        "is_dated": true,
        "year": 2014,
        "gregorian_year": 2014,
        "mint_letter": "J",
        "mintage": 77000,
        "comment": "Proof"
    }
]